ectocet/__init__.py
ectocet-0.1.0.dist-info/WHEEL
ectocet-0.1.0.dist-info/METADATA
ectocet-0.1.0.dist-info/RECORD
