Metadata-Version: 2.1
Name: ectocet
Version: 0.1.0
Summary: 
Author: guillaumervls
Author-email: 3765057+guillaumervls@users.noreply.github.com
Requires-Python: >=3.9,<4.0
Classifier: Programming Language :: Python :: 3
Classifier: Programming Language :: Python :: 3.10
Classifier: Programming Language :: Python :: 3.9
Requires-Dist: requests (>=2.27.1,<3.0.0)
